Workbook

Sheet 📋 Cover
B2: NimbusHR Inc. — Cybersecurity Risk Register
B3: Aligned to NIST Cybersecurity Framework 2.0 | Prepared by: Donnie V Haynes
B5: DOCUMENT INFORMATION
B6: Document Title | C6: NimbusHR Cybersecurity Risk Register
B7: Version | C7: 1.0 — Initial Release
B8: Prepared By | C8: Donnie V Haynes (Portfolio Project)
B9: Framework | C9: NIST Cybersecurity Framework 2.0
B10: Classification | C10: Confidential — Internal Use Only
B11: Review Cycle | C11: Monthly review | Annual reassessment
B12: Last Updated | C12: 2024
B14: HOW TO USE THIS REGISTER
B15: 📊 Risk Register tab | C15: The main working document. Each row is one risk. Update Status, Residual Score, and Notes as controls are implemented.
B16: 📈 Dashboard tab | C16: Auto-calculated summary. Shows risk counts by rating, treatment strategy breakdown, and open vs closed items.
B17: 📚 Reference tab | C17: Definitions for all column values — risk ratings, treatment strategies, status codes, and NIST CSF function descriptions.
B18: 🔄 Update frequency | C18: The register should be reviewed monthly by the Risk Owner and formally reassessed annually or after any material security incident.
B19: ➕ Adding new risks | C19: Insert a new row in the Risk Register, assign the next sequential Risk ID (R-009, R-010, etc.), and complete all columns.
B20: ✅ Closing a risk | C20: When a risk is fully remediated, change Status to CLOSED and set the Residual Score to reflect remaining exposure. Do not delete rows.
B22: RISK RATING SCALE
B23: 🔴 CRITICAL (20–25) | C23: Immediate action required. Escalate to senior leadership.
B24: 🟠 HIGH (12–19) | C24: Remediate within 30–60 days. Assign owner, track to closure.
B25: 🟡 MEDIUM (6–11) | C25: Remediate within 90 days. Document compensating controls.
B26: 🟢 LOW (1–5) | C26: Monitor and review at next scheduled assessment cycle.

Sheet 📊 Risk Register
A1: NimbusHR Inc. | Cybersecurity Risk Register | NIST CSF 2.0 | Prepared by: Donnie V Haynes | Version 1.0 | 2024
A2: Risk ID | B2: Risk Title | C2: Category | D2: Description | E2: Threat Source | F2: Affected Assets | G2: NIST CSF Ref | H2: Likelihood (1–5) | I2: Impact (1–5) | J2: Inherent Risk Score | K2: Inherent Rating | L2: Treatment Strategy | M2: Controls In Place | N2: Additional Controls Required | O2: Risk Owner | P2: Target Date | Q2: Residual Likelihood | R2: Residual Impact | S2: Residual Risk Score | T2: Residual Rating | U2: Status | V2: Last Reviewed | W2: Notes
A3: R-001 | B3: No MFA on Administrative Accounts | C3: Access Control | D3: Admin and privileged AWS accounts lack MFA. A credential compromise would grant full cloud environment access including all stored PII. | E3: External Attacker / Insider | F3: AWS Root Account, IAM Admin Roles, Console Access | G3: PR.AA-03, PR.AA-05 | H3: 5 | I3: 5 | J3: =H3*I3 -> 25 | K3: CRITICAL | L3: Mitigate | M3: Password policy enforced. IAM users require unique credentials. | N3: Enable MFA on root account and all IAM console users. Enforce via SCP. Deploy hardware tokens for privileged accounts. | O3: IT Manager | P3: 2024-01-15 | Q3: 2 | R3: 5 | S3: =Q3*R3 -> 10 | T3: MEDIUM | U3: IN PROGRESS | V3: 2024-01-01 | W3: MFA enabled on root account. Rollout to IAM users underway. SCP policy drafted.
A4: R-002 | B4: Insufficient Encryption of PII at Rest | C4: Data Protection | D4: Not all S3 buckets have default encryption enabled. KMS key rotation not configured on RDS. PII exposed if buckets are misconfigured or accessed without authorisation. | E4: External Attacker / Misconfiguration | F4: AWS S3 Buckets, RDS Database | G4: PR.DS-01, PR.DS-02 | H4: 4 | I4: 5 | J4: =H4*I4 -> 20 | K4: CRITICAL | L4: Mitigate | M4: RDS encryption enabled at rest. TLS enforced in transit. | N4: Enable S3 default encryption (AES-256/KMS) on all buckets. Enable KMS key auto-rotation. Deploy AWS Config rule for unencrypted resources. | O4: IT Manager | P4: 2024-01-15 | Q4: 2 | R4: 5 | S4: =Q4*R4 -> 10 | T4: MEDIUM | U4: IN PROGRESS | V4: 2024-01-01 | W4: S3 encryption audit in progress. 14 of 22 buckets remediated.
A5: R-003 | B5: No Incident Response Plan | C5: Incident Readiness | D5: No documented IRP exists. Staff have no established procedures for detection, containment, notification, or recovery in the event of a breach or ransomware incident. | E5: All Threat Actors | F5: All Systems / Business Continuity | G5: RS.MA-01, RS.CO-02, RC.RP-01 | H5: 4 | I5: 4 | J5: =H5*I5 -> 16 | K5: HIGH | L5: Mitigate | M5: None. No documented IRP, playbooks, or escalation contacts exist. | N5: Draft IRP covering: incident classification, roles, containment, comms, and recovery. Conduct tabletop exercise within 30 days of publication. | O5: IT Manager | P5: 2024-02-28 | Q5: 3 | R5: 4 | S5: =Q5*R5 -> 12 | T5: HIGH | U5: OPEN | V5: 2024-01-01 | W5: IRP drafting not yet started. Assigned to IT Manager. High priority.
A6: R-004 | B6: No Security Awareness Training | C6: Human Factor | D6: No mandatory security awareness training programme. Employees are susceptible to phishing, social engineering, and unsafe data-handling practices. | E6: Phishing / Social Engineering | F6: All Employees / Email / Credentials | G6: GV.RR-02, PR.AT-01 | H6: 4 | I6: 4 | J6: =H6*I6 -> 16 | K6: HIGH | L6: Mitigate | M6: Informal guidance shared via Slack. No structured programme. | N6: Deploy training platform (KnowBe4 free tier or equivalent). Require annual completion. Run quarterly simulated phishing campaigns. | O6: HR + IT Manager | P6: 2024-02-28 | Q6: 2 | R6: 4 | S6: =Q6*R6 -> 8 | T6: MEDIUM | U6: OPEN | V6: 2024-01-01 | W6: Evaluating KnowBe4 and Proofpoint free tiers. Budget approval pending.
A7: R-005 | B7: No Patch Management Programme | C7: Patch Management | D7: No documented patching schedule. Open-source library dependencies in the web application may contain known CVEs. No vulnerability scanner deployed. | E7: External Attacker / Opportunistic | F7: Web Application, AWS EC2, OS / Libraries | G7: ID.RA-01, PR.PS-02 | H7: 3 | I7: 4 | J7: =H7*I7 -> 12 | K7: HIGH | L7: Mitigate | M7: Ad-hoc patching performed by developers. No formal SLA. | N7: Define monthly patch cycle. Deploy Dependabot in GitHub CI/CD. Deploy AWS Inspector for infrastructure scanning. Set CVE SLAs. | O7: Engineering Lead | P7: 2024-03-31 | Q7: 2 | R7: 4 | S7: =Q7*R7 -> 8 | T7: MEDIUM | U7: OPEN | V7: 2024-01-01 | W7: Dependabot can be enabled on GitHub at no cost. Quick win.
A8: R-006 | B8: Excessive Privileges / No Access Reviews | C8: Access Control | D8: Developer and support accounts hold broader IAM permissions than role requires. No formal access review. Former employees may retain active credentials. | E8: Insider Threat / Compromised Account | F8: AWS IAM, Internal Systems, S3, RDS | G8: PR.AA-01, PR.AA-05, ID.AM-03 | H8: 3 | I8: 3 | J8: =H8*I8 -> 9 | K8: MEDIUM | L8: Mitigate | M8: Unique IAM credentials per user. No shared accounts. | N8: Conduct immediate IAM access review. Implement least-privilege. Create off-boarding checklist. Schedule quarterly access certifications. | O8: IT Manager | P8: 2024-03-31 | Q8: 2 | R8: 3 | S8: =Q8*R8 -> 6 | T8: MEDIUM | U8: OPEN | V8: 2024-01-01 | W8: IAM Access Analyzer available at no cost in AWS console.
A9: R-007 | B9: Insufficient Logging and Monitoring | C9: Incident Readiness | D9: CloudTrail enabled but logs not actively monitored. No alerts on critical events. Attackers could operate undetected for extended periods. | E9: All Threat Actors | F9: AWS CloudTrail, CloudWatch, All Infrastructure | G9: DE.CM-01, DE.AE-02, PR.PS-04 | H9: 3 | I9: 3 | J9: =H9*I9 -> 9 | K9: MEDIUM | L9: Mitigate | M9: AWS CloudTrail enabled in primary region. Logs stored in S3. | N9: Enable CloudTrail in all regions. Configure CloudWatch alerts for: root logins, IAM changes, large S3 downloads, failed auth spikes. | O9: IT Manager | P9: 2024-03-31 | Q9: 2 | R9: 3 | S9: =Q9*R9 -> 6 | T9: MEDIUM | U9: OPEN | V9: 2024-01-01 | W9: CloudWatch alerting is low-cost. Estimate <$20/month for alert rules.
A10: R-008 | B10: Unassessed Third-Party Vendor Risk | C10: Third-Party Risk | D10: Payroll API integration transmits salary and banking data to a third party that has not been formally security assessed. No DPA or VSQ in place. | E10: Supply Chain / Third-Party Breach | F10: Payroll Integration API, Client Salary Data | G10: GV.SC-04, GV.SC-06 | H10: 2 | I10: 3 | J10: =H10*I10 -> 6 | K10: MEDIUM | L10: Transfer | M10: TLS encryption on API calls. Contractual SLA with vendor. | N10: Issue vendor security questionnaire (VSQ). Request SOC 2 report. Ensure Data Processing Agreement (DPA) is executed. | O10: Legal + IT Manager | P10: 2024-04-30 | Q10: 2 | R10: 3 | S10: =Q10*R10 -> 6 | T10: MEDIUM | U10: OPEN | V10: 2024-01-01 | W10: VSQ template available from NIST SP 800-161. Low effort, high value.

Sheet 📈 Dashboard
B1: NimbusHR Risk Register — Executive Dashboard
B2: Auto-calculated from Risk Register | Prepared by: Donnie V Haynes | NIST CSF 2.0
B4: ▸ RISK COUNTS — INHERENT RATING
B5: 🔴 CRITICAL risks | C5: =COUNTIF('📊 Risk Register'!K3:K10,"CRITICAL") -> 2
B6: 🟠 HIGH risks | C6: =COUNTIF('📊 Risk Register'!K3:K10,"HIGH") -> 3
B7: 🟡 MEDIUM risks | C7: =COUNTIF('📊 Risk Register'!K3:K10,"MEDIUM") -> 3
B8: 🟢 LOW risks | C8: =COUNTIF('📊 Risk Register'!K3:K10,"LOW") -> 0
B9: 📋 Total risks | C9: =COUNTA('📊 Risk Register'!A3:A10) -> 8
B11: ▸ RISK STATUS BREAKDOWN
B12: 🔓 Open | C12: =COUNTIF('📊 Risk Register'!U3:U10,"OPEN") -> 6
B13: 🔄 In Progress | C13: =COUNTIF('📊 Risk Register'!U3:U10,"IN PROGRESS") -> 2
B14: ✅ Closed | C14: =COUNTIF('📊 Risk Register'!U3:U10,"CLOSED") -> 0
B15: 📌 Accepted | C15: =COUNTIF('📊 Risk Register'!U3:U10,"ACCEPTED") -> 0
B17: ▸ TREATMENT STRATEGY BREAKDOWN
B18: 🛡️ Mitigate | C18: =COUNTIF('📊 Risk Register'!L3:L10,"Mitigate") -> 7
B19: 🔄 Transfer | C19: =COUNTIF('📊 Risk Register'!L3:L10,"Transfer") -> 1
B20: 📋 Accept | C20: =COUNTIF('📊 Risk Register'!L3:L10,"Accept") -> 0
B21: 🚫 Avoid | C21: =COUNTIF('📊 Risk Register'!L3:L10,"Avoid") -> 0
B23: ▸ RISK REDUCTION SUMMARY (Inherent vs Residual)
B24: Risk ID | C24: Risk Title | E24: Inherent Score | F24: Residual Score | G24: Score Reduction
B25: R-001 | C25: No MFA on Administrative Accounts | E25: ='📊 Risk Register'!J3 -> 25 | F25: ='📊 Risk Register'!S3 -> 10 | G25: =E25-F25 -> 15
B26: R-002 | C26: Insufficient Encryption of PII at Rest | E26: ='📊 Risk Register'!J4 -> 20 | F26: ='📊 Risk Register'!S4 -> 10 | G26: =E26-F26 -> 10
B27: R-003 | C27: No Incident Response Plan | E27: ='📊 Risk Register'!J5 -> 16 | F27: ='📊 Risk Register'!S5 -> 12 | G27: =E27-F27 -> 4
B28: R-004 | C28: No Security Awareness Training | E28: ='📊 Risk Register'!J6 -> 16 | F28: ='📊 Risk Register'!S6 -> 8 | G28: =E28-F28 -> 8
B29: R-005 | C29: No Patch Management Programme | E29: ='📊 Risk Register'!J7 -> 12 | F29: ='📊 Risk Register'!S7 -> 8 | G29: =E29-F29 -> 4
B30: R-006 | C30: Excessive Privileges / No Access Reviews | E30: ='📊 Risk Register'!J8 -> 9 | F30: ='📊 Risk Register'!S8 -> 6 | G30: =E30-F30 -> 3
B31: R-007 | C31: Insufficient Logging and Monitoring | E31: ='📊 Risk Register'!J9 -> 9 | F31: ='📊 Risk Register'!S9 -> 6 | G31: =E31-F31 -> 3
B32: R-008 | C32: Unassessed Third-Party Vendor Risk | E32: ='📊 Risk Register'!J10 -> 6 | F32: ='📊 Risk Register'!S10 -> 6 | G32: =E32-F32 -> 0

Sheet 📚 Reference
B1: Reference Guide — Definitions & Framework Mappings
B3: RISK RATING SCALE
B4: CRITICAL (Score 20–25) | C4: Immediate remediation required. Escalate to senior leadership. Risk to core business operations.
B5: HIGH (Score 12–19) | C5: Remediate within 30–60 days. Assign a named owner. Track to closure at every review.
B6: MEDIUM (Score 6–11) | C6: Remediate within 90 days. Document any compensating controls in place.
B7: LOW (Score 1–5) | C7: Monitor at next scheduled review cycle. Compensating controls may be sufficient.
B9: TREATMENT STRATEGIES
B10: Mitigate | C10: Implement controls to reduce likelihood or impact. Most common strategy — applies to the majority of technical risks.
B11: Transfer | C11: Shift financial liability to a third party (e.g., cyber liability insurance, contractual indemnity, managed security provider).
B12: Accept | C12: Acknowledge the risk exists but make a documented decision that cost of remediation exceeds benefit. Requires management sign-off.
B13: Avoid | C13: Eliminate the activity or system that creates the risk entirely. E.g., stop using an insecure third-party tool.
B15: STATUS CODES
B16: OPEN | C16: Risk identified. No remediation action taken yet. Requires an assigned owner and target date.
B17: IN PROGRESS | C17: Remediation underway. Controls being implemented. Check notes column for progress details.
B18: CLOSED | C18: Risk fully remediated. Controls implemented and verified. Residual score updated to reflect remaining exposure.
B19: ACCEPTED | C19: Risk formally accepted by management. Documented rationale required. Review at next cycle.
B21: NIST CSF 2.0 — CORE FUNCTIONS
B22: GOVERN (GV) | C22: Establishes organizational context, risk strategy, roles, policies, and oversight. New in CSF 2.0. Foundation of all other functions.
B23: IDENTIFY (ID) | C23: Understand the organization's assets, risks, and vulnerabilities. Includes asset management and risk assessment.
B24: PROTECT (PR) | C24: Implement safeguards to limit the impact of cybersecurity events. Includes access control, data protection, and training.
B25: DETECT (DE) | C25: Develop and implement activities to identify cybersecurity events in a timely manner. Includes monitoring and anomaly detection.
B26: RESPOND (RS) | C26: Take action regarding a detected cybersecurity incident. Includes response planning, communications, and analysis.
B27: RECOVER (RC) | C27: Restore capabilities impaired by a cybersecurity incident. Includes recovery planning and communications.
B29: RISK SCORING METHODOLOGY
B30: Inherent Risk Score | C30: Likelihood (1–5) × Impact (1–5) = Raw score BEFORE any controls are applied. Represents worst-case exposure.
B31: Residual Risk Score | C31: Likelihood (1–5) × Impact (1–5) = Score AFTER controls are implemented. Should decrease as remediation progresses.
B32: Likelihood Scale | C32: 1=Rare, 2=Unlikely, 3=Possible, 4=Likely, 5=Almost Certain. Based on threat frequency and existing control environment.
B33: Impact Scale | C33: 1=Negligible, 2=Minor, 3=Moderate, 4=Major, 5=Catastrophic. Based on financial, reputational, legal, and operational impact.
